[
  {
    "item": "home",
    "schoolname": "The University of Utah",
    "abbreviation": "UniUtah",
    "genericProgramName": "The Global Career Accelerator",
    "secondaryBrandColor": "#000000",
    "primaryBrandColor": "#BE0000",
    "buttonColor": "#BE0000",
    "buttonTextColor": "#FFFFFF",
    "logo": "https://d15k2d11r6t6rl.cloudfront.net/public/users/Integrators/669d5713-9b6a-46bb-bd7e-c542cff6dd6a/bad0d961febe4f229536d370ebbb97ed/logo-school-dynamic-email/utah.png",
    "cobranded_logo": "https://d15k2d11r6t6rl.cloudfront.net/public/users/Integrators/669d5713-9b6a-46bb-bd7e-c542cff6dd6a/bad0d961febe4f229536d370ebbb97ed/logo-school-cobrand-gca-dynamic-email/utah.png",
    "partner_id": "001Rd00000Ks0PLIAZ",
    "programName": "Utah Global Career Accelerator",
    "termsandConditionsPolicy": null,
    "registrationMessage": "Registration is now open.",
    "credits": "3 or 6 UniUtah credits",
    "startDate": "May 20",
    "endDate": "August 6"
  },
  {
    "item": "about",
    "schoolname": "The University of Utah",
    "genericProgramName": "The Global Career Accelerator",
    "schoolFullAddress": "201 Presidents' Cir, Salt Lake City, UT 84112",
    "abbreviation": "UniUtah",
    "phone": "(801) 876-1581",
    "credits": "3 or 6 UniUtah credits",
    "programFee": null,
    "seasonYear": "Summer 2026",
    "term": "Summer",
    "season": "Summer",
    "registrationMessage": "Registration is now open."
  },
  {
    "item": "explore-tracks",
    "credits": "3 or 6 UniUtah credits",
    "abbreviation": "UniUtah",
    "registrationMessage": "Registration is now open."
  },
  {
    "item": "digital-marketing",
    "schoolname": "The University of Utah",
    "trackTitle": "Digital Marketing Track",
    "credits": "3 or 6 UniUtah credits",
    "abbreviation": "UniUtah",
    "registrationMessage": "Registration is now open.",
    "courseCode1": "HNKLY 4903-002 (CRN: 17479)",
    "courseCode2": "HNKLY 4903-002 (CRN: 17479)",
    "seasonYear1": "Summer 2026",
    "seasonYear2": "Fall 2026",
    "term1StartDate": "May 20",
    "term1EndDate": "August 6",
    "term2StartDate": "August 24",
    "term2EndDate": "December 10"
  },
  {
    "item": "coding-for-web",
    "schoolname": "The University of Utah",
    "trackTitle": "Web Development for Everyone Track",
    "credits": "3 or 6 UniUtah credits",
    "abbreviation": "UniUtah",
    "registrationMessage": "Registration is now open.",
    "courseCode1": "HNKLY 4903-002 (CRN: 17479)",
    "courseCode2": "HNKLY 4903-002 (CRN: 17479)",
    "seasonYear1": "Summer 2026",
    "seasonYear2": "Fall 2026",
    "term1StartDate": "May 20",
    "term1EndDate": "August 6",
    "term2StartDate": "August 24",
    "term2EndDate": "December 10"
  },
  {
    "item": "data-analytics",
    "schoolname": "The University of Utah",
    "trackTitle": "Data Analytics Track",
    "credits": "3 or 6 UniUtah credits",
    "abbreviation": "UniUtah",
    "registrationMessage": "Registration is now open.",
    "courseCode1": "HNKLY 4903-002 (CRN: 17479)",
    "courseCode2": "HNKLY 4903-002 (CRN: 17479)",
    "seasonYear1": "Summer 2026",
    "seasonYear2": "Fall 2026",
    "term1StartDate": "May 20",
    "term1EndDate": "August 6",
    "term2StartDate": "August 24",
    "term2EndDate": "December 10"
  },
  {
    "item": "coding-for-data",
    "schoolname": "The University of Utah",
    "trackTitle": "Coding for Data Track",
    "credits": "3 or 6 UniUtah credits",
    "abbreviation": "UniUtah",
    "registrationMessage": "Registration is now open.",
    "courseCode1": "HNKLY 4903-002 (CRN: 17479)",
    "courseCode2": "HNKLY 4903-002 (CRN: 17479)",
    "seasonYear1": "Summer 2026",
    "seasonYear2": "Fall 2026",
    "term1StartDate": "May 20",
    "term1EndDate": "August 6",
    "term2StartDate": "August 24",
    "term2EndDate": "December 10"
  },
  {
    "item": "career-rotation",
    "schoolname": "The University of Utah",
    "trackTitle": "Career Rotation Track",
    "credits": "3 or 6 UniUtah credits",
    "abbreviation": "UniUtah",
    "registrationMessage": "Registration is now open.",
    "courseCode1": "HNKLY 4903-002 (CRN: 17479)",
    "courseCode2": "HNKLY 4903-002 (CRN: 17479)",
    "seasonYear1": "Summer 2026",
    "seasonYear2": "Fall 2026",
    "term1StartDate": "May 20",
    "term1EndDate": "August 6",
    "term2StartDate": "August 24",
    "term2EndDate": "December 10"
  },
  {
    "item": "reserve-a-seat",
    "programName": "Utah Global Career Accelerator",
    "registrationMessage": "Registration is now open.",
    "phone": "(801) 876-1581",
    "abbreviation": "UniUtah"
  },
  {
    "item": "begin",
    "credits": "3 or 6 UniUtah credits",
    "abbreviation": "UniUtah",
    "phone": "(801) 876-1581"
  }
]